[
  {
    "word": "started.  docker's",
    "start": 84.045,
    "end": 85.659
  },
  {
    "word": "a",
    "start": 85.693,
    "end": 85.728
  },
  {
    "word": "form",
    "start": 85.81,
    "end": 86.111
  },
  {
    "word": "of",
    "start": 86.169,
    "end": 86.227
  },
  {
    "word": "virtualization,",
    "start": 86.32,
    "end": 87.435
  },
  {
    "word": "but",
    "start": 87.714,
    "end": 87.864
  },
  {
    "word": "unlike",
    "start": 87.923,
    "end": 88.236
  },
  {
    "word": "virtual",
    "start": 88.294,
    "end": 88.654
  },
  {
    "word": "machines,",
    "start": 88.712,
    "end": 89.304
  },
  {
    "word": "the",
    "start": 89.478,
    "end": 89.594
  },
  {
    "word": "resources",
    "start": 89.687,
    "end": 90.268
  },
  {
    "word": "are",
    "start": 90.337,
    "end": 90.465
  },
  {
    "word": "shared",
    "start": 90.5,
    "end": 90.79
  },
  {
    "word": "directly",
    "start": 90.86,
    "end": 91.394
  },
  {
    "word": "with",
    "start": 91.429,
    "end": 91.568
  },
  {
    "word": "the",
    "start": 91.603,
    "end": 91.672
  },
  {
    "word": "host.",
    "start": 91.719,
    "end": 92.183
  },
  {
    "word": "This",
    "start": 92.694,
    "end": 92.88
  },
  {
    "word": "allows",
    "start": 92.926,
    "end": 93.217
  },
  {
    "word": "you",
    "start": 93.263,
    "end": 93.344
  },
  {
    "word": "to",
    "start": 93.402,
    "end": 93.46
  },
  {
    "word": "run",
    "start": 93.542,
    "end": 93.716
  },
  {
    "word": "many",
    "start": 93.809,
    "end": 94.064
  },
  {
    "word": "docker",
    "start": 94.122,
    "end": 94.389
  },
  {
    "word": "containers",
    "start": 94.424,
    "end": 94.993
  },
  {
    "word": "where",
    "start": 95.167,
    "end": 95.376
  },
  {
    "word": "you",
    "start": 95.411,
    "end": 95.481
  },
  {
    "word": "might",
    "start": 95.539,
    "end": 95.748
  },
  {
    "word": "only",
    "start": 95.817,
    "end": 96.177
  },
  {
    "word": "be",
    "start": 96.247,
    "end": 96.351
  },
  {
    "word": "able",
    "start": 96.409,
    "end": 96.63
  },
  {
    "word": "to",
    "start": 96.665,
    "end": 96.734
  },
  {
    "word": "run",
    "start": 96.816,
    "end": 96.967
  },
  {
    "word": "a",
    "start": 97.001,
    "end": 97.036
  },
  {
    "word": "few",
    "start": 97.118,
    "end": 97.35
  },
  {
    "word": "virtual",
    "start": 97.466,
    "end": 97.872
  },
  {
    "word": "machines.",
    "start": 97.93,
    "end": 98.557
  },
  {
    "word": "A",
    "start": 99.254,
    "end": 99.335
  },
  {
    "word": "virtual",
    "start": 99.416,
    "end": 99.788
  },
  {
    "word": "machine",
    "start": 99.857,
    "end": 100.357
  },
  {
    "word": "has",
    "start": 100.473,
    "end": 100.659
  },
  {
    "word": "to",
    "start": 100.717,
    "end": 100.786
  },
  {
    "word": "quarantine",
    "start": 100.868,
    "end": 101.413
  },
  {
    "word": "off",
    "start": 101.448,
    "end": 101.553
  },
  {
    "word": "a",
    "start": 101.611,
    "end": 101.634
  },
  {
    "word": "set",
    "start": 101.703,
    "end": 101.901
  },
  {
    "word": "amount",
    "start": 101.936,
    "end": 102.156
  },
  {
    "word": "of",
    "start": 102.191,
    "end": 102.238
  },
  {
    "word": "resources,",
    "start": 102.296,
    "end": 103.015
  },
  {
    "word": "hard",
    "start": 103.294,
    "end": 103.515
  },
  {
    "word": "drive",
    "start": 103.55,
    "end": 103.805
  },
  {
    "word": "space,",
    "start": 103.828,
    "end": 104.304
  },
  {
    "word": "memory,",
    "start": 104.513,
    "end": 105.013
  },
  {
    "word": "and",
    "start": 105.129,
    "end": 105.268
  },
  {
    "word": "processing",
    "start": 105.338,
    "end": 105.837
  },
  {
    "word": "power,",
    "start": 105.895,
    "end": 106.301
  },
  {
    "word": "emulate",
    "start": 106.51,
    "end": 106.952
  },
  {
    "word": "hardware,",
    "start": 106.986,
    "end": 107.532
  },
  {
    "word": "and",
    "start": 107.706,
    "end": 107.857
  },
  {
    "word": "then",
    "start": 107.915,
    "end": 108.078
  },
  {
    "word": "boot",
    "start": 108.147,
    "end": 108.345
  },
  {
    "word": "an",
    "start": 108.414,
    "end": 108.484
  },
  {
    "word": "entire",
    "start": 108.542,
    "end": 109.053
  },
  {
    "word": "operating",
    "start": 109.123,
    "end": 109.587
  },
  {
    "word": "system.",
    "start": 109.645,
    "end": 110.109
  },
  {
    "word": "The",
    "start": 110.62,
    "end": 110.748
  },
  {
    "word": "V",
    "start": 110.818,
    "end": 110.887
  },
  {
    "word": "M",
    "start": 111.061,
    "end": 111.236
  },
  {
    "word": "then",
    "start": 111.329,
    "end": 111.514
  },
  {
    "word": "communicates",
    "start": 111.584,
    "end": 112.153
  },
  {
    "word": "with",
    "start": 112.176,
    "end": 112.292
  },
  {
    "word": "the",
    "start": 112.327,
    "end": 112.397
  },
  {
    "word": "host",
    "start": 112.455,
    "end": 112.687
  },
  {
    "word": "computer",
    "start": 112.745,
    "end": 113.221
  },
  {
    "word": "via",
    "start": 113.395,
    "end": 113.697
  },
  {
    "word": "a",
    "start": 113.743,
    "end": 113.778
  },
  {
    "word": "translator",
    "start": 113.825,
    "end": 114.359
  },
  {
    "word": "application",
    "start": 114.394,
    "end": 114.951
  },
  {
    "word": "running",
    "start": 115.229,
    "end": 115.508
  },
  {
    "word": "on",
    "start": 115.555,
    "end": 115.624
  },
  {
    "word": "the",
    "start": 115.671,
    "end": 115.74
  },
  {
    "word": "host",
    "start": 115.81,
    "end": 116.065
  },
  {
    "word": "operating",
    "start": 116.123,
    "end": 116.541
  },
  {
    "word": "system",
    "start": 116.599,
    "end": 116.936
  },
  {
    "word": "called",
    "start": 117.18,
    "end": 117.528
  },
  {
    "word": "a",
    "start": 117.644,
    "end": 117.76
  },
  {
    "word": "hypervisor.  docker",
    "start": 117.853,
    "end": 119.722
  },
  {
    "word": "communicates",
    "start": 119.792,
    "end": 120.361
  },
  {
    "word": "natively",
    "start": 120.43,
    "end": 120.837
  },
  {
    "word": "with",
    "start": 120.895,
    "end": 121.034
  },
  {
    "word": "the",
    "start": 121.069,
    "end": 121.139
  },
  {
    "word": "system",
    "start": 121.197,
    "end": 121.522
  },
  {
    "word": "kernel,",
    "start": 121.591,
    "end": 122.044
  },
  {
    "word": "bypassing",
    "start": 122.218,
    "end": 122.868
  },
  {
    "word": "the",
    "start": 122.915,
    "end": 122.985
  },
  {
    "word": "middleman",
    "start": 123.031,
    "end": 123.461
  },
  {
    "word": "on",
    "start": 123.553,
    "end": 123.716
  },
  {
    "word": "Linux",
    "start": 123.809,
    "end": 124.111
  },
  {
    "word": "machines,",
    "start": 124.169,
    "end": 124.749
  },
  {
    "word": "and",
    "start": 124.923,
    "end": 125.074
  },
  {
    "word": "even",
    "start": 125.144,
    "end": 125.341
  },
  {
    "word": "Windows",
    "start": 125.411,
    "end": 125.783
  },
  {
    "word": "10",
    "start": 125.852,
    "end": 126.108
  },
  {
    "word": "and",
    "start": 126.386,
    "end": 126.607
  },
  {
    "word": "Windows",
    "start": 126.688,
    "end": 127.048
  },
  {
    "word": "Server",
    "start": 127.095,
    "end": 127.408
  },
  {
    "word": "2016",
    "start": 127.489,
    "end": 128.232
  },
  {
    "word": "and",
    "start": 128.348,
    "end": 128.569
  },
  {
    "word": "above.",
    "start": 128.627,
    "end": 129.08
  },
  {
    "word": "This",
    "start": 129.893,
    "end": 130.136
  },
  {
    "word": "means",
    "start": 130.206,
    "end": 130.496
  },
  {
    "word": "you",
    "start": 130.566,
    "end": 130.67
  },
  {
    "word": "can",
    "start": 130.717,
    "end": 130.833
  },
  {
    "word": "run",
    "start": 130.891,
    "end": 131.077
  },
  {
    "word": "any",
    "start": 131.193,
    "end": 131.46
  },
  {
    "word": "version",
    "start": 131.53,
    "end": 131.843
  },
  {
    "word": "of",
    "start": 131.889,
    "end": 131.936
  },
  {
    "word": "Linux",
    "start": 131.994,
    "end": 132.249
  },
  {
    "word": "in",
    "start": 132.331,
    "end": 132.435
  },
  {
    "word": "a",
    "start": 132.482,
    "end": 132.505
  },
  {
    "word": "container",
    "start": 132.551,
    "end": 133.074
  },
  {
    "word": "and",
    "start": 133.248,
    "end": 133.445
  },
  {
    "word": "it'll",
    "start": 133.503,
    "end": 133.677
  },
  {
    "word": "run",
    "start": 133.723,
    "end": 133.898
  },
  {
    "word": "natively.  docker",
    "start": 133.979,
    "end": 135.558
  },
  {
    "word": "also",
    "start": 135.651,
    "end": 136.057
  },
  {
    "word": "uses",
    "start": 136.138,
    "end": 136.429
  },
  {
    "word": "less",
    "start": 136.51,
    "end": 136.719
  },
  {
    "word": "disk",
    "start": 136.777,
    "end": 137.032
  },
  {
    "word": "space,",
    "start": 137.09,
    "end": 137.566
  },
  {
    "word": "as",
    "start": 137.694,
    "end": 137.845
  },
  {
    "word": "it",
    "start": 137.903,
    "end": 137.973
  },
  {
    "word": "reuses",
    "start": 138.042,
    "end": 138.553
  },
  {
    "word": "files",
    "start": 138.623,
    "end": 138.983
  },
  {
    "word": "efficiently",
    "start": 139.029,
    "end": 139.633
  },
  {
    "word": "through",
    "start": 139.784,
    "end": 140.051
  },
  {
    "word": "a",
    "start": 140.086,
    "end": 140.109
  },
  {
    "word": "layered",
    "start": 140.19,
    "end": 140.527
  },
  {
    "word": "file",
    "start": 140.585,
    "end": 140.875
  },
  {
    "word": "system.",
    "start": 140.91,
    "end": 141.444
  },
  {
    "word": "If",
    "start": 142.048,
    "end": 142.176
  },
  {
    "word": "you",
    "start": 142.222,
    "end": 142.303
  },
  {
    "word": "have",
    "start": 142.361,
    "end": 142.501
  },
  {
    "word": "multiple",
    "start": 142.57,
    "end": 143.035
  },
  {
    "word": "docker",
    "start": 143.081,
    "end": 143.36
  },
  {
    "word": "images",
    "start": 143.406,
    "end": 143.801
  },
  {
    "word": "using",
    "start": 143.882,
    "end": 144.138
  },
  {
    "word": "the",
    "start": 144.184,
    "end": 144.254
  },
  {
    "word": "same",
    "start": 144.347,
    "end": 144.683
  },
  {
    "word": "base",
    "start": 144.741,
    "end": 145.008
  },
  {
    "word": "image,",
    "start": 145.043,
    "end": 145.484
  },
  {
    "word": "docker",
    "start": 145.809,
    "end": 146.169
  },
  {
    "word": "only",
    "start": 146.239,
    "end": 146.425
  },
  {
    "word": "keeps",
    "start": 146.471,
    "end": 146.727
  },
  {
    "word": "a",
    "start": 146.761,
    "end": 146.796
  },
  {
    "word": "single",
    "start": 146.889,
    "end": 147.237
  },
  {
    "word": "copy",
    "start": 147.284,
    "end": 147.563
  },
  {
    "word": "of",
    "start": 147.609,
    "end": 147.667
  },
  {
    "word": "the",
    "start": 147.702,
    "end": 147.772
  },
  {
    "word": "files",
    "start": 147.83,
    "end": 148.213
  },
  {
    "word": "needed",
    "start": 148.271,
    "end": 148.596
  },
  {
    "word": "and",
    "start": 148.747,
    "end": 148.967
  },
  {
    "word": "shares",
    "start": 149.037,
    "end": 149.362
  },
  {
    "word": "them",
    "start": 149.409,
    "end": 149.525
  },
  {
    "word": "with",
    "start": 149.571,
    "end": 149.711
  },
  {
    "word": "each",
    "start": 149.792,
    "end": 150.001
  }
]